{"exchangeRateCurrency":"bot:currencies","responseContent":[{"period":"27 Dec 2002","currency_id":"MYR","countryName":"Malaysia","currency_name_th":"มาเลเซีย : ริงกิต (MYR)","currency_name_eng":"MALAYSIA : RINGGIT (MYR)","buying_sight":"11.0154","buying_transfer":"11.0837","selling":"11.6490","flagPath":"/content/dam/bot/currencyflags/MYR.png","sortOrder":6},{"period":"26 Dec 2002","currency_id":"MYR","countryName":"Malaysia","currency_name_th":"มาเลเซีย : ริงกิต (MYR)","currency_name_eng":"MALAYSIA : RINGGIT (MYR)","buying_sight":"10.9297","buying_transfer":"10.9839","selling":"11.6914","flagPath":"/content/dam/bot/currencyflags/MYR.png","sortOrder":6},{"period":"25 Dec 2002","currency_id":"MYR","countryName":"Malaysia","currency_name_th":"มาเลเซีย : ริงกิต (MYR)","currency_name_eng":"MALAYSIA : RINGGIT (MYR)","buying_sight":"10.9878","buying_transfer":"11.0595","selling":"11.5775","flagPath":"/content/dam/bot/currencyflags/MYR.png","sortOrder":6},{"period":"24 Dec 2002","currency_id":"MYR","countryName":"Malaysia","currency_name_th":"มาเลเซีย : ริงกิต (MYR)","currency_name_eng":"MALAYSIA : RINGGIT (MYR)","buying_sight":"10.9849","buying_transfer":"11.0784","selling":"11.5799","flagPath":"/content/dam/bot/currencyflags/MYR.png","sortOrder":6},{"period":"23 Dec 2002","currency_id":"MYR","countryName":"Malaysia","currency_name_th":"มาเลเซีย : ริงกิต (MYR)","currency_name_eng":"MALAYSIA : RINGGIT (MYR)","buying_sight":"10.9885","buying_transfer":"11.0573","selling":"11.6233","flagPath":"/content/dam/bot/currencyflags/MYR.png","sortOrder":6},{"period":"20 Dec 2002","currency_id":"MYR","countryName":"Malaysia","currency_name_th":"มาเลเซีย : ริงกิต (MYR)","currency_name_eng":"MALAYSIA : RINGGIT (MYR)","buying_sight":"11.0022","buying_transfer":"11.0724","selling":"11.5865","flagPath":"/content/dam/bot/currencyflags/MYR.png","sortOrder":6},{"period":"19 Dec 2002","currency_id":"MYR","countryName":"Malaysia","currency_name_th":"มาเลเซีย : ริงกิต (MYR)","currency_name_eng":"MALAYSIA : RINGGIT (MYR)","buying_sight":"10.9962","buying_transfer":"11.0674","selling":"11.5816","flagPath":"/content/dam/bot/currencyflags/MYR.png","sortOrder":6},{"period":"18 Dec 2002","currency_id":"MYR","countryName":"Malaysia","currency_name_th":"มาเลเซีย : ริงกิต (MYR)","currency_name_eng":"MALAYSIA : RINGGIT (MYR)","buying_sight":"11.0439","buying_transfer":"11.1056","selling":"11.5773","flagPath":"/content/dam/bot/currencyflags/MYR.png","sortOrder":6},{"period":"17 Dec 2002","currency_id":"MYR","countryName":"Malaysia","currency_name_th":"มาเลเซีย : ริงกิต (MYR)","currency_name_eng":"MALAYSIA : RINGGIT (MYR)","buying_sight":"11.0436","buying_transfer":"11.1047","selling":"11.6263","flagPath":"/content/dam/bot/currencyflags/MYR.png","sortOrder":6},{"period":"16 Dec 2002","currency_id":"MYR","countryName":"Malaysia","currency_name_th":"มาเลเซีย : ริงกิต (MYR)","currency_name_eng":"MALAYSIA : RINGGIT (MYR)","buying_sight":"11.0105","buying_transfer":"11.0764","selling":"11.6848","flagPath":"/content/dam/bot/currencyflags/MYR.png","sortOrder":6},{"period":"13 Dec 2002","currency_id":"MYR","countryName":"Malaysia","currency_name_th":"มาเลเซีย : ริงกิต (MYR)","currency_name_eng":"MALAYSIA : RINGGIT (MYR)","buying_sight":"11.1044","buying_transfer":"11.1794","selling":"11.6290","flagPath":"/content/dam/bot/currencyflags/MYR.png","sortOrder":6},{"period":"12 Dec 2002","currency_id":"MYR","countryName":"Malaysia","currency_name_th":"มาเลเซีย : ริงกิต (MYR)","currency_name_eng":"MALAYSIA : RINGGIT (MYR)","buying_sight":"11.0895","buying_transfer":"11.1612","selling":"11.6817","flagPath":"/content/dam/bot/currencyflags/MYR.png","sortOrder":6},{"period":"11 Dec 2002","currency_id":"MYR","countryName":"Malaysia","currency_name_th":"มาเลเซีย : ริงกิต (MYR)","currency_name_eng":"MALAYSIA : RINGGIT (MYR)","buying_sight":"11.1261","buying_transfer":"11.2012","selling":"11.6509","flagPath":"/content/dam/bot/currencyflags/MYR.png","sortOrder":6},{"period":"09 Dec 2002","currency_id":"MYR","countryName":"Malaysia","currency_name_th":"มาเลเซีย : ริงกิต (MYR)","currency_name_eng":"MALAYSIA : RINGGIT (MYR)","buying_sight":"11.1255","buying_transfer":"11.1979","selling":"11.7197","flagPath":"/content/dam/bot/currencyflags/MYR.png","sortOrder":6},{"period":"06 Dec 2002","currency_id":"MYR","countryName":"Malaysia","currency_name_th":"มาเลเซีย : ริงกิต (MYR)","currency_name_eng":"MALAYSIA : RINGGIT (MYR)","buying_sight":"11.2184","buying_transfer":"11.2932","selling":"11.7464","flagPath":"/content/dam/bot/currencyflags/MYR.png","sortOrder":6},{"period":"04 Dec 2002","currency_id":"MYR","countryName":"Malaysia","currency_name_th":"มาเลเซีย : ริงกิต (MYR)","currency_name_eng":"MALAYSIA : RINGGIT (MYR)","buying_sight":"11.1482","buying_transfer":"11.2208","selling":"11.7438","flagPath":"/content/dam/bot/currencyflags/MYR.png","sortOrder":6},{"period":"03 Dec 2002","currency_id":"MYR","countryName":"Malaysia","currency_name_th":"มาเลเซีย : ริงกิต (MYR)","currency_name_eng":"MALAYSIA : RINGGIT (MYR)","buying_sight":"11.2042","buying_transfer":"11.2778","selling":"11.7307","flagPath":"/content/dam/bot/currencyflags/MYR.png","sortOrder":6},{"period":"02 Dec 2002","currency_id":"MYR","countryName":"Malaysia","currency_name_th":"มาเลเซีย : ริงกิต (MYR)","currency_name_eng":"MALAYSIA : RINGGIT (MYR)","buying_sight":"11.1331","buying_transfer":"11.2098","selling":"11.7322","flagPath":"/content/dam/bot/currencyflags/MYR.png","sortOrder":6},{"period":"29 Nov 2002","currency_id":"MYR","countryName":"Malaysia","currency_name_th":"มาเลเซีย : ริงกิต (MYR)","currency_name_eng":"MALAYSIA : RINGGIT (MYR)","buying_sight":"11.0949","buying_transfer":"11.1663","selling":"11.6869","flagPath":"/content/dam/bot/currencyflags/MYR.png","sortOrder":6},{"period":"28 Nov 2002","currency_id":"MYR","countryName":"Malaysia","currency_name_th":"มาเลเซีย : ริงกิต (MYR)","currency_name_eng":"MALAYSIA : RINGGIT (MYR)","buying_sight":"11.1287","buying_transfer":"11.2031","selling":"11.6533","flagPath":"/content/dam/bot/currencyflags/MYR.png","sortOrder":6},{"period":"27 Nov 2002","currency_id":"MYR","countryName":"Malaysia","currency_name_th":"มาเลเซีย : ริงกิต (MYR)","currency_name_eng":"MALAYSIA : RINGGIT (MYR)","buying_sight":"11.0978","buying_transfer":"11.1688","selling":"11.6897","flagPath":"/content/dam/bot/currencyflags/MYR.png","sortOrder":6},{"period":"26 Nov 2002","currency_id":"MYR","countryName":"Malaysia","currency_name_th":"มาเลเซีย : ริงกิต (MYR)","currency_name_eng":"MALAYSIA : RINGGIT (MYR)","buying_sight":"11.0924","buying_transfer":"11.1641","selling":"11.6829","flagPath":"/content/dam/bot/currencyflags/MYR.png","sortOrder":6},{"period":"25 Nov 2002","currency_id":"MYR","countryName":"Malaysia","currency_name_th":"มาเลเซีย : ริงกิต (MYR)","currency_name_eng":"MALAYSIA : RINGGIT (MYR)","buying_sight":"11.0999","buying_transfer":"11.1713","selling":"11.6924","flagPath":"/content/dam/bot/currencyflags/MYR.png","sortOrder":6},{"period":"22 Nov 2002","currency_id":"MYR","countryName":"Malaysia","currency_name_th":"มาเลเซีย : ริงกิต (MYR)","currency_name_eng":"MALAYSIA : RINGGIT (MYR)","buying_sight":"11.1547","buying_transfer":"11.2174","selling":"11.6266","flagPath":"/content/dam/bot/currencyflags/MYR.png","sortOrder":6},{"period":"21 Nov 2002","currency_id":"MYR","countryName":"Malaysia","currency_name_th":"มาเลเซีย : ริงกิต (MYR)","currency_name_eng":"MALAYSIA : RINGGIT (MYR)","buying_sight":"11.0755","buying_transfer":"11.1438","selling":"11.7116","flagPath":"/content/dam/bot/currencyflags/MYR.png","sortOrder":6},{"period":"20 Nov 2002","currency_id":"MYR","countryName":"Malaysia","currency_name_th":"มาเลเซีย : ริงกิต (MYR)","currency_name_eng":"MALAYSIA : RINGGIT (MYR)","buying_sight":"11.1122","buying_transfer":"11.1837","selling":"11.7060","flagPath":"/content/dam/bot/currencyflags/MYR.png","sortOrder":6},{"period":"19 Nov 2002","currency_id":"MYR","countryName":"Malaysia","currency_name_th":"มาเลเซีย : ริงกิต (MYR)","currency_name_eng":"MALAYSIA : RINGGIT (MYR)","buying_sight":"11.1266","buying_transfer":"11.2005","selling":"11.6509","flagPath":"/content/dam/bot/currencyflags/MYR.png","sortOrder":6},{"period":"18 Nov 2002","currency_id":"MYR","countryName":"Malaysia","currency_name_th":"มาเลเซีย : ริงกิต (MYR)","currency_name_eng":"MALAYSIA : RINGGIT (MYR)","buying_sight":"11.1255","buying_transfer":"11.1957","selling":"11.7119","flagPath":"/content/dam/bot/currencyflags/MYR.png","sortOrder":6},{"period":"15 Nov 2002","currency_id":"MYR","countryName":"Malaysia","currency_name_th":"มาเลเซีย : ริงกิต (MYR)","currency_name_eng":"MALAYSIA : RINGGIT (MYR)","buying_sight":"11.0577","buying_transfer":"11.1220","selling":"11.7667","flagPath":"/content/dam/bot/currencyflags/MYR.png","sortOrder":6},{"period":"14 Nov 2002","currency_id":"MYR","countryName":"Malaysia","currency_name_th":"มาเลเซีย : ริงกิต (MYR)","currency_name_eng":"MALAYSIA : RINGGIT (MYR)","buying_sight":"11.0886","buying_transfer":"11.1601","selling":"11.6773","flagPath":"/content/dam/bot/currencyflags/MYR.png","sortOrder":6},{"period":"13 Nov 2002","currency_id":"MYR","countryName":"Malaysia","currency_name_th":"มาเลเซีย : ริงกิต (MYR)","currency_name_eng":"MALAYSIA : RINGGIT (MYR)","buying_sight":"11.0360","buying_transfer":"11.1077","selling":"11.6258","flagPath":"/content/dam/bot/currencyflags/MYR.png","sortOrder":6},{"period":"12 Nov 2002","currency_id":"MYR","countryName":"Malaysia","currency_name_th":"มาเลเซีย : ริงกิต (MYR)","currency_name_eng":"MALAYSIA : RINGGIT (MYR)","buying_sight":"11.0225","buying_transfer":"11.0928","selling":"11.6108","flagPath":"/content/dam/bot/currencyflags/MYR.png","sortOrder":6},{"period":"11 Nov 2002","currency_id":"MYR","countryName":"Malaysia","currency_name_th":"มาเลเซีย : ริงกิต (MYR)","currency_name_eng":"MALAYSIA : RINGGIT (MYR)","buying_sight":"10.9883","buying_transfer":"11.0588","selling":"11.5755","flagPath":"/content/dam/bot/currencyflags/MYR.png","sortOrder":6},{"period":"08 Nov 2002","currency_id":"MYR","countryName":"Malaysia","currency_name_th":"มาเลเซีย : ริงกิต (MYR)","currency_name_eng":"MALAYSIA : RINGGIT (MYR)","buying_sight":"11.0458","buying_transfer":"11.1168","selling":"11.6299","flagPath":"/content/dam/bot/currencyflags/MYR.png","sortOrder":6},{"period":"07 Nov 2002","currency_id":"MYR","countryName":"Malaysia","currency_name_th":"มาเลเซีย : ริงกิต (MYR)","currency_name_eng":"MALAYSIA : RINGGIT (MYR)","buying_sight":"11.0939","buying_transfer":"11.1676","selling":"11.6164","flagPath":"/content/dam/bot/currencyflags/MYR.png","sortOrder":6},{"period":"06 Nov 2002","currency_id":"MYR","countryName":"Malaysia","currency_name_th":"มาเลเซีย : ริงกิต (MYR)","currency_name_eng":"MALAYSIA : RINGGIT (MYR)","buying_sight":"11.0612","buying_transfer":"11.1316","selling":"11.6508","flagPath":"/content/dam/bot/currencyflags/MYR.png","sortOrder":6},{"period":"05 Nov 2002","currency_id":"MYR","countryName":"Malaysia","currency_name_th":"มาเลเซีย : ริงกิต (MYR)","currency_name_eng":"MALAYSIA : RINGGIT (MYR)","buying_sight":"11.0778","buying_transfer":"11.1514","selling":"11.5998","flagPath":"/content/dam/bot/currencyflags/MYR.png","sortOrder":6},{"period":"04 Nov 2002","currency_id":"MYR","countryName":"Malaysia","currency_name_th":"มาเลเซีย : ริงกิต (MYR)","currency_name_eng":"MALAYSIA : RINGGIT (MYR)","buying_sight":"11.0892","buying_transfer":"11.1634","selling":"11.6124","flagPath":"/content/dam/bot/currencyflags/MYR.png","sortOrder":6},{"period":"01 Nov 2002","currency_id":"MYR","countryName":"Malaysia","currency_name_th":"มาเลเซีย : ริงกิต (MYR)","currency_name_eng":"MALAYSIA : RINGGIT (MYR)","buying_sight":"11.1070","buying_transfer":"11.1807","selling":"11.6305","flagPath":"/content/dam/bot/currencyflags/MYR.png","sortOrder":6},{"period":"31 Oct 2002","currency_id":"MYR","countryName":"Malaysia","currency_name_th":"มาเลเซีย : ริงกิต (MYR)","currency_name_eng":"MALAYSIA : RINGGIT (MYR)","buying_sight":"11.0816","buying_transfer":"11.1534","selling":"11.6736","flagPath":"/content/dam/bot/currencyflags/MYR.png","sortOrder":6},{"period":"30 Oct 2002","currency_id":"MYR","countryName":"Malaysia","currency_name_th":"มาเลเซีย : ริงกิต (MYR)","currency_name_eng":"MALAYSIA : RINGGIT (MYR)","buying_sight":"11.0932","buying_transfer":"11.1638","selling":"11.6809","flagPath":"/content/dam/bot/currencyflags/MYR.png","sortOrder":6},{"period":"29 Oct 2002","currency_id":"MYR","countryName":"Malaysia","currency_name_th":"มาเลเซีย : ริงกิต (MYR)","currency_name_eng":"MALAYSIA : RINGGIT (MYR)","buying_sight":"11.1226","buying_transfer":"11.1959","selling":"11.6458","flagPath":"/content/dam/bot/currencyflags/MYR.png","sortOrder":6},{"period":"28 Oct 2002","currency_id":"MYR","countryName":"Malaysia","currency_name_th":"มาเลเซีย : ริงกิต (MYR)","currency_name_eng":"MALAYSIA : RINGGIT (MYR)","buying_sight":"11.1121","buying_transfer":"11.1857","selling":"11.7079","flagPath":"/content/dam/bot/currencyflags/MYR.png","sortOrder":6},{"period":"25 Oct 2002","currency_id":"MYR","countryName":"Malaysia","currency_name_th":"มาเลเซีย : ริงกิต (MYR)","currency_name_eng":"MALAYSIA : RINGGIT (MYR)","buying_sight":"11.1579","buying_transfer":"11.2320","selling":"11.6836","flagPath":"/content/dam/bot/currencyflags/MYR.png","sortOrder":6},{"period":"24 Oct 2002","currency_id":"MYR","countryName":"Malaysia","currency_name_th":"มาเลเซีย : ริงกิต (MYR)","currency_name_eng":"MALAYSIA : RINGGIT (MYR)","buying_sight":"11.1369","buying_transfer":"11.2095","selling":"11.7277","flagPath":"/content/dam/bot/currencyflags/MYR.png","sortOrder":6},{"period":"22 Oct 2002","currency_id":"MYR","countryName":"Malaysia","currency_name_th":"มาเลเซีย : ริงกิต (MYR)","currency_name_eng":"MALAYSIA : RINGGIT (MYR)","buying_sight":"11.1427","buying_transfer":"11.2153","selling":"11.7383","flagPath":"/content/dam/bot/currencyflags/MYR.png","sortOrder":6},{"period":"21 Oct 2002","currency_id":"MYR","countryName":"Malaysia","currency_name_th":"มาเลเซีย : ริงกิต (MYR)","currency_name_eng":"MALAYSIA : RINGGIT (MYR)","buying_sight":"11.1807","buying_transfer":"11.2537","selling":"11.7706","flagPath":"/content/dam/bot/currencyflags/MYR.png","sortOrder":6},{"period":"18 Oct 2002","currency_id":"MYR","countryName":"Malaysia","currency_name_th":"มาเลเซีย : ริงกิต (MYR)","currency_name_eng":"MALAYSIA : RINGGIT (MYR)","buying_sight":"11.2228","buying_transfer":"11.2963","selling":"11.7506","flagPath":"/content/dam/bot/currencyflags/MYR.png","sortOrder":6},{"period":"17 Oct 2002","currency_id":"MYR","countryName":"Malaysia","currency_name_th":"มาเลเซีย : ริงกิต (MYR)","currency_name_eng":"MALAYSIA : RINGGIT (MYR)","buying_sight":"11.2000","buying_transfer":"11.2725","selling":"11.7917","flagPath":"/content/dam/bot/currencyflags/MYR.png","sortOrder":6},{"period":"16 Oct 2002","currency_id":"MYR","countryName":"Malaysia","currency_name_th":"มาเลเซีย : ริงกิต (MYR)","currency_name_eng":"MALAYSIA : RINGGIT (MYR)","buying_sight":"11.2079","buying_transfer":"11.2724","selling":"11.9220","flagPath":"/content/dam/bot/currencyflags/MYR.png","sortOrder":6},{"period":"15 Oct 2002","currency_id":"MYR","countryName":"Malaysia","currency_name_th":"มาเลเซีย : ริงกิต (MYR)","currency_name_eng":"MALAYSIA : RINGGIT (MYR)","buying_sight":"11.2857","buying_transfer":"11.3573","selling":"11.8862","flagPath":"/content/dam/bot/currencyflags/MYR.png","sortOrder":6},{"period":"14 Oct 2002","currency_id":"MYR","countryName":"Malaysia","currency_name_th":"มาเลเซีย : ริงกิต (MYR)","currency_name_eng":"MALAYSIA : RINGGIT (MYR)","buying_sight":"11.2483","buying_transfer":"11.3224","selling":"11.8491","flagPath":"/content/dam/bot/currencyflags/MYR.png","sortOrder":6},{"period":"11 Oct 2002","currency_id":"MYR","countryName":"Malaysia","currency_name_th":"มาเลเซีย : ริงกิต (MYR)","currency_name_eng":"MALAYSIA : RINGGIT (MYR)","buying_sight":"11.2197","buying_transfer":"11.2919","selling":"11.8184","flagPath":"/content/dam/bot/currencyflags/MYR.png","sortOrder":6},{"period":"10 Oct 2002","currency_id":"MYR","countryName":"Malaysia","currency_name_th":"มาเลเซีย : ริงกิต (MYR)","currency_name_eng":"MALAYSIA : RINGGIT (MYR)","buying_sight":"11.1848","buying_transfer":"11.2571","selling":"11.7807","flagPath":"/content/dam/bot/currencyflags/MYR.png","sortOrder":6},{"period":"09 Oct 2002","currency_id":"MYR","countryName":"Malaysia","currency_name_th":"มาเลเซีย : ริงกิต (MYR)","currency_name_eng":"MALAYSIA : RINGGIT (MYR)","buying_sight":"11.1790","buying_transfer":"11.2500","selling":"11.7754","flagPath":"/content/dam/bot/currencyflags/MYR.png","sortOrder":6},{"period":"08 Oct 2002","currency_id":"MYR","countryName":"Malaysia","currency_name_th":"มาเลเซีย : ริงกิต (MYR)","currency_name_eng":"MALAYSIA : RINGGIT (MYR)","buying_sight":"11.1983","buying_transfer":"11.2703","selling":"11.7909","flagPath":"/content/dam/bot/currencyflags/MYR.png","sortOrder":6},{"period":"07 Oct 2002","currency_id":"MYR","countryName":"Malaysia","currency_name_th":"มาเลเซีย : ริงกิต (MYR)","currency_name_eng":"MALAYSIA : RINGGIT (MYR)","buying_sight":"11.1274","buying_transfer":"11.1941","selling":"11.8063","flagPath":"/content/dam/bot/currencyflags/MYR.png","sortOrder":6},{"period":"04 Oct 2002","currency_id":"MYR","countryName":"Malaysia","currency_name_th":"มาเลเซีย : ริงกิต (MYR)","currency_name_eng":"MALAYSIA : RINGGIT (MYR)","buying_sight":"11.1188","buying_transfer":"11.1906","selling":"11.7126","flagPath":"/content/dam/bot/currencyflags/MYR.png","sortOrder":6},{"period":"03 Oct 2002","currency_id":"MYR","countryName":"Malaysia","currency_name_th":"มาเลเซีย : ริงกิต (MYR)","currency_name_eng":"MALAYSIA : RINGGIT (MYR)","buying_sight":"11.1263","buying_transfer":"11.1980","selling":"11.7205","flagPath":"/content/dam/bot/currencyflags/MYR.png","sortOrder":6},{"period":"02 Oct 2002","currency_id":"MYR","countryName":"Malaysia","currency_name_th":"มาเลเซีย : ริงกิต (MYR)","currency_name_eng":"MALAYSIA : RINGGIT (MYR)","buying_sight":"11.1710","buying_transfer":"11.2457","selling":"11.6973","flagPath":"/content/dam/bot/currencyflags/MYR.png","sortOrder":6},{"period":"01 Oct 2002","currency_id":"MYR","countryName":"Malaysia","currency_name_th":"มาเลเซีย : ริงกิต (MYR)","currency_name_eng":"MALAYSIA : RINGGIT (MYR)","buying_sight":"11.0979","buying_transfer":"11.1692","selling":"11.6900","flagPath":"/content/dam/bot/currencyflags/MYR.png","sortOrder":6},{"period":"30 Sep 2002","currency_id":"MYR","countryName":"Malaysia","currency_name_th":"มาเลเซีย : ริงกิต (MYR)","currency_name_eng":"MALAYSIA : RINGGIT (MYR)","buying_sight":"11.0443","buying_transfer":"11.1084","selling":"11.7520","flagPath":"/content/dam/bot/currencyflags/MYR.png","sortOrder":6},{"period":"27 Sep 2002","currency_id":"MYR","countryName":"Malaysia","currency_name_th":"มาเลเซีย : ริงกิต (MYR)","currency_name_eng":"MALAYSIA : RINGGIT (MYR)","buying_sight":"11.0987","buying_transfer":"11.1699","selling":"11.6908","flagPath":"/content/dam/bot/currencyflags/MYR.png","sortOrder":6},{"period":"26 Sep 2002","currency_id":"MYR","countryName":"Malaysia","currency_name_th":"มาเลเซีย : ริงกิต (MYR)","currency_name_eng":"MALAYSIA : RINGGIT (MYR)","buying_sight":"11.1264","buying_transfer":"11.1969","selling":"11.7186","flagPath":"/content/dam/bot/currencyflags/MYR.png","sortOrder":6},{"period":"25 Sep 2002","currency_id":"MYR","countryName":"Malaysia","currency_name_th":"มาเลเซีย : ริงกิต (MYR)","currency_name_eng":"MALAYSIA : RINGGIT (MYR)","buying_sight":"11.1034","buying_transfer":"11.1748","selling":"11.6917","flagPath":"/content/dam/bot/currencyflags/MYR.png","sortOrder":6},{"period":"24 Sep 2002","currency_id":"MYR","countryName":"Malaysia","currency_name_th":"มาเลเซีย : ริงกิต (MYR)","currency_name_eng":"MALAYSIA : RINGGIT (MYR)","buying_sight":"11.1033","buying_transfer":"11.1743","selling":"11.6955","flagPath":"/content/dam/bot/currencyflags/MYR.png","sortOrder":6},{"period":"23 Sep 2002","currency_id":"MYR","countryName":"Malaysia","currency_name_th":"มาเลเซีย : ริงกิต (MYR)","currency_name_eng":"MALAYSIA : RINGGIT (MYR)","buying_sight":"11.0786","buying_transfer":"11.1500","selling":"11.6700","flagPath":"/content/dam/bot/currencyflags/MYR.png","sortOrder":6},{"period":"20 Sep 2002","currency_id":"MYR","countryName":"Malaysia","currency_name_th":"มาเลเซีย : ริงกิต (MYR)","currency_name_eng":"MALAYSIA : RINGGIT (MYR)","buying_sight":"11.0304","buying_transfer":"11.0993","selling":"11.6670","flagPath":"/content/dam/bot/currencyflags/MYR.png","sortOrder":6},{"period":"19 Sep 2002","currency_id":"MYR","countryName":"Malaysia","currency_name_th":"มาเลเซีย : ริงกิต (MYR)","currency_name_eng":"MALAYSIA : RINGGIT (MYR)","buying_sight":"10.9878","buying_transfer":"11.0608","selling":"11.5730","flagPath":"/content/dam/bot/currencyflags/MYR.png","sortOrder":6},{"period":"18 Sep 2002","currency_id":"MYR","countryName":"Malaysia","currency_name_th":"มาเลเซีย : ริงกิต (MYR)","currency_name_eng":"MALAYSIA : RINGGIT (MYR)","buying_sight":"10.9691","buying_transfer":"11.0374","selling":"11.6027","flagPath":"/content/dam/bot/currencyflags/MYR.png","sortOrder":6},{"period":"17 Sep 2002","currency_id":"MYR","countryName":"Malaysia","currency_name_th":"มาเลเซีย : ริงกิต (MYR)","currency_name_eng":"MALAYSIA : RINGGIT (MYR)","buying_sight":"11.0466","buying_transfer":"11.1097","selling":"11.6556","flagPath":"/content/dam/bot/currencyflags/MYR.png","sortOrder":6},{"period":"16 Sep 2002","currency_id":"MYR","countryName":"Malaysia","currency_name_th":"มาเลเซีย : ริงกิต (MYR)","currency_name_eng":"MALAYSIA : RINGGIT (MYR)","buying_sight":"10.9771","buying_transfer":"11.0405","selling":"11.6436","flagPath":"/content/dam/bot/currencyflags/MYR.png","sortOrder":6},{"period":"13 Sep 2002","currency_id":"MYR","countryName":"Malaysia","currency_name_th":"มาเลเซีย : ริงกิต (MYR)","currency_name_eng":"MALAYSIA : RINGGIT (MYR)","buying_sight":"10.8780","buying_transfer":"10.9345","selling":"11.4460","flagPath":"/content/dam/bot/currencyflags/MYR.png","sortOrder":6},{"period":"12 Sep 2002","currency_id":"MYR","countryName":"Malaysia","currency_name_th":"มาเลเซีย : ริงกิต (MYR)","currency_name_eng":"MALAYSIA : RINGGIT (MYR)","buying_sight":"10.8510","buying_transfer":"10.9207","selling":"11.4275","flagPath":"/content/dam/bot/currencyflags/MYR.png","sortOrder":6},{"period":"11 Sep 2002","currency_id":"MYR","countryName":"Malaysia","currency_name_th":"มาเลเซีย : ริงกิต (MYR)","currency_name_eng":"MALAYSIA : RINGGIT (MYR)","buying_sight":"10.8873","buying_transfer":"10.9616","selling":"11.4033","flagPath":"/content/dam/bot/currencyflags/MYR.png","sortOrder":6},{"period":"10 Sep 2002","currency_id":"MYR","countryName":"Malaysia","currency_name_th":"มาเลเซีย : ริงกิต (MYR)","currency_name_eng":"MALAYSIA : RINGGIT (MYR)","buying_sight":"10.8376","buying_transfer":"10.9080","selling":"11.4186","flagPath":"/content/dam/bot/currencyflags/MYR.png","sortOrder":6},{"period":"09 Sep 2002","currency_id":"MYR","countryName":"Malaysia","currency_name_th":"มาเลเซีย : ริงกิต (MYR)","currency_name_eng":"MALAYSIA : RINGGIT (MYR)","buying_sight":"10.8495","buying_transfer":"10.9207","selling":"11.3615","flagPath":"/content/dam/bot/currencyflags/MYR.png","sortOrder":6},{"period":"06 Sep 2002","currency_id":"MYR","countryName":"Malaysia","currency_name_th":"มาเลเซีย : ริงกิต (MYR)","currency_name_eng":"MALAYSIA : RINGGIT (MYR)","buying_sight":"10.8597","buying_transfer":"10.9199","selling":"11.3052","flagPath":"/content/dam/bot/currencyflags/MYR.png","sortOrder":6},{"period":"05 Sep 2002","currency_id":"MYR","countryName":"Malaysia","currency_name_th":"มาเลเซีย : ริงกิต (MYR)","currency_name_eng":"MALAYSIA : RINGGIT (MYR)","buying_sight":"10.7832","buying_transfer":"10.8545","selling":"11.3677","flagPath":"/content/dam/bot/currencyflags/MYR.png","sortOrder":6},{"period":"04 Sep 2002","currency_id":"MYR","countryName":"Malaysia","currency_name_th":"มาเลเซีย : ริงกิต (MYR)","currency_name_eng":"MALAYSIA : RINGGIT (MYR)","buying_sight":"10.8057","buying_transfer":"10.8778","selling":"11.3214","flagPath":"/content/dam/bot/currencyflags/MYR.png","sortOrder":6},{"period":"03 Sep 2002","currency_id":"MYR","countryName":"Malaysia","currency_name_th":"มาเลเซีย : ริงกิต (MYR)","currency_name_eng":"MALAYSIA : RINGGIT (MYR)","buying_sight":"10.8754","buying_transfer":"10.9489","selling":"11.2954","flagPath":"/content/dam/bot/currencyflags/MYR.png","sortOrder":6},{"period":"02 Sep 2002","currency_id":"MYR","countryName":"Malaysia","currency_name_th":"มาเลเซีย : ริงกิต (MYR)","currency_name_eng":"MALAYSIA : RINGGIT (MYR)","buying_sight":"10.8786","buying_transfer":"10.9525","selling":"11.2992","flagPath":"/content/dam/bot/currencyflags/MYR.png","sortOrder":6},{"period":"30 Aug 2002","currency_id":"MYR","countryName":"Malaysia","currency_name_th":"มาเลเซีย : ริงกิต (MYR)","currency_name_eng":"MALAYSIA : RINGGIT (MYR)","buying_sight":"10.8208","buying_transfer":"10.8940","selling":"11.3379","flagPath":"/content/dam/bot/currencyflags/MYR.png","sortOrder":6},{"period":"29 Aug 2002","currency_id":"MYR","countryName":"Malaysia","currency_name_th":"มาเลเซีย : ริงกิต (MYR)","currency_name_eng":"MALAYSIA : RINGGIT (MYR)","buying_sight":"10.8450","buying_transfer":"10.9181","selling":"11.3628","flagPath":"/content/dam/bot/currencyflags/MYR.png","sortOrder":6},{"period":"28 Aug 2002","currency_id":"MYR","countryName":"Malaysia","currency_name_th":"มาเลเซีย : ริงกิต (MYR)","currency_name_eng":"MALAYSIA : RINGGIT (MYR)","buying_sight":"10.7785","buying_transfer":"10.8494","selling":"11.3629","flagPath":"/content/dam/bot/currencyflags/MYR.png","sortOrder":6},{"period":"27 Aug 2002","currency_id":"MYR","countryName":"Malaysia","currency_name_th":"มาเลเซีย : ริงกิต (MYR)","currency_name_eng":"MALAYSIA : RINGGIT (MYR)","buying_sight":"10.8071","buying_transfer":"10.8789","selling":"11.3930","flagPath":"/content/dam/bot/currencyflags/MYR.png","sortOrder":6},{"period":"26 Aug 2002","currency_id":"MYR","countryName":"Malaysia","currency_name_th":"มาเลเซีย : ริงกิต (MYR)","currency_name_eng":"MALAYSIA : RINGGIT (MYR)","buying_sight":"10.8095","buying_transfer":"10.8801","selling":"11.3948","flagPath":"/content/dam/bot/currencyflags/MYR.png","sortOrder":6},{"period":"23 Aug 2002","currency_id":"MYR","countryName":"Malaysia","currency_name_th":"มาเลเซีย : ริงกิต (MYR)","currency_name_eng":"MALAYSIA : RINGGIT (MYR)","buying_sight":"10.8268","buying_transfer":"10.8993","selling":"11.4149","flagPath":"/content/dam/bot/currencyflags/MYR.png","sortOrder":6},{"period":"22 Aug 2002","currency_id":"MYR","countryName":"Malaysia","currency_name_th":"มาเลเซีย : ริงกิต (MYR)","currency_name_eng":"MALAYSIA : RINGGIT (MYR)","buying_sight":"10.8022","buying_transfer":"10.8763","selling":"11.3196","flagPath":"/content/dam/bot/currencyflags/MYR.png","sortOrder":6},{"period":"21 Aug 2002","currency_id":"MYR","countryName":"Malaysia","currency_name_th":"มาเลเซีย : ริงกิต (MYR)","currency_name_eng":"MALAYSIA : RINGGIT (MYR)","buying_sight":"10.7518","buying_transfer":"10.8245","selling":"11.3370","flagPath":"/content/dam/bot/currencyflags/MYR.png","sortOrder":6},{"period":"20 Aug 2002","currency_id":"MYR","countryName":"Malaysia","currency_name_th":"มาเลเซีย : ริงกิต (MYR)","currency_name_eng":"MALAYSIA : RINGGIT (MYR)","buying_sight":"10.7509","buying_transfer":"10.8230","selling":"11.3233","flagPath":"/content/dam/bot/currencyflags/MYR.png","sortOrder":6},{"period":"19 Aug 2002","currency_id":"MYR","countryName":"Malaysia","currency_name_th":"มาเลเซีย : ริงกิต (MYR)","currency_name_eng":"MALAYSIA : RINGGIT (MYR)","buying_sight":"10.7524","buying_transfer":"10.8114","selling":"11.2064","flagPath":"/content/dam/bot/currencyflags/MYR.png","sortOrder":6},{"period":"16 Aug 2002","currency_id":"MYR","countryName":"Malaysia","currency_name_th":"มาเลเซีย : ริงกิต (MYR)","currency_name_eng":"MALAYSIA : RINGGIT (MYR)","buying_sight":"10.6874","buying_transfer":"10.7566","selling":"11.2660","flagPath":"/content/dam/bot/currencyflags/MYR.png","sortOrder":6},{"period":"15 Aug 2002","currency_id":"MYR","countryName":"Malaysia","currency_name_th":"มาเลเซีย : ริงกิต (MYR)","currency_name_eng":"MALAYSIA : RINGGIT (MYR)","buying_sight":"10.7272","buying_transfer":"10.8003","selling":"11.3153","flagPath":"/content/dam/bot/currencyflags/MYR.png","sortOrder":6},{"period":"14 Aug 2002","currency_id":"MYR","countryName":"Malaysia","currency_name_th":"มาเลเซีย : ริงกิต (MYR)","currency_name_eng":"MALAYSIA : RINGGIT (MYR)","buying_sight":"10.7336","buying_transfer":"10.8053","selling":"11.3207","flagPath":"/content/dam/bot/currencyflags/MYR.png","sortOrder":6},{"period":"13 Aug 2002","currency_id":"MYR","countryName":"Malaysia","currency_name_th":"มาเลเซีย : ริงกิต (MYR)","currency_name_eng":"MALAYSIA : RINGGIT (MYR)","buying_sight":"10.8107","buying_transfer":"10.8838","selling":"11.3321","flagPath":"/content/dam/bot/currencyflags/MYR.png","sortOrder":6},{"period":"09 Aug 2002","currency_id":"MYR","countryName":"Malaysia","currency_name_th":"มาเลเซีย : ริงกิต (MYR)","currency_name_eng":"MALAYSIA : RINGGIT (MYR)","buying_sight":"10.8601","buying_transfer":"10.9324","selling":"11.4405","flagPath":"/content/dam/bot/currencyflags/MYR.png","sortOrder":6},{"period":"08 Aug 2002","currency_id":"MYR","countryName":"Malaysia","currency_name_th":"มาเลเซีย : ริงกิต (MYR)","currency_name_eng":"MALAYSIA : RINGGIT (MYR)","buying_sight":"10.8378","buying_transfer":"10.9098","selling":"11.4303","flagPath":"/content/dam/bot/currencyflags/MYR.png","sortOrder":6},{"period":"07 Aug 2002","currency_id":"MYR","countryName":"Malaysia","currency_name_th":"มาเลเซีย : ริงกิต (MYR)","currency_name_eng":"MALAYSIA : RINGGIT (MYR)","buying_sight":"10.8617","buying_transfer":"10.9303","selling":"11.4477","flagPath":"/content/dam/bot/currencyflags/MYR.png","sortOrder":6},{"period":"06 Aug 2002","currency_id":"MYR","countryName":"Malaysia","currency_name_th":"มาเลเซีย : ริงกิต (MYR)","currency_name_eng":"MALAYSIA : RINGGIT (MYR)","buying_sight":"10.8213","buying_transfer":"10.8888","selling":"11.4564","flagPath":"/content/dam/bot/currencyflags/MYR.png","sortOrder":6},{"period":"05 Aug 2002","currency_id":"MYR","countryName":"Malaysia","currency_name_th":"มาเลเซีย : ริงกิต (MYR)","currency_name_eng":"MALAYSIA : RINGGIT (MYR)","buying_sight":"10.7349","buying_transfer":"10.7988","selling":"11.3583","flagPath":"/content/dam/bot/currencyflags/MYR.png","sortOrder":6},{"period":"02 Aug 2002","currency_id":"MYR","countryName":"Malaysia","currency_name_th":"มาเลเซีย : ริงกิต (MYR)","currency_name_eng":"MALAYSIA : RINGGIT (MYR)","buying_sight":"10.7571","buying_transfer":"10.8284","selling":"11.3447","flagPath":"/content/dam/bot/currencyflags/MYR.png","sortOrder":6},{"period":"01 Aug 2002","currency_id":"MYR","countryName":"Malaysia","currency_name_th":"มาเลเซีย : ริงกิต (MYR)","currency_name_eng":"MALAYSIA : RINGGIT (MYR)","buying_sight":"10.6672","buying_transfer":"10.7269","selling":"11.3577","flagPath":"/content/dam/bot/currencyflags/MYR.png","sortOrder":6},{"period":"31 Jul 2002","currency_id":"MYR","countryName":"Malaysia","currency_name_th":"มาเลเซีย : ริงกิต (MYR)","currency_name_eng":"MALAYSIA : RINGGIT (MYR)","buying_sight":"10.7195","buying_transfer":"10.7889","selling":"11.3455","flagPath":"/content/dam/bot/currencyflags/MYR.png","sortOrder":6},{"period":"30 Jul 2002","currency_id":"MYR","countryName":"Malaysia","currency_name_th":"มาเลเซีย : ริงกิต (MYR)","currency_name_eng":"MALAYSIA : RINGGIT (MYR)","buying_sight":"10.6833","buying_transfer":"10.7501","selling":"11.3806","flagPath":"/content/dam/bot/currencyflags/MYR.png","sortOrder":6},{"period":"29 Jul 2002","currency_id":"MYR","countryName":"Malaysia","currency_name_th":"มาเลเซีย : ริงกิต (MYR)","currency_name_eng":"MALAYSIA : RINGGIT (MYR)","buying_sight":"10.7648","buying_transfer":"10.8203","selling":"11.4836","flagPath":"/content/dam/bot/currencyflags/MYR.png","sortOrder":6},{"period":"26 Jul 2002","currency_id":"MYR","countryName":"Malaysia","currency_name_th":"มาเลเซีย : ริงกิต (MYR)","currency_name_eng":"MALAYSIA : RINGGIT (MYR)","buying_sight":"10.5256","buying_transfer":"10.5707","selling":"11.1937","flagPath":"/content/dam/bot/currencyflags/MYR.png","sortOrder":6},{"period":"24 Jul 2002","currency_id":"MYR","countryName":"Malaysia","currency_name_th":"มาเลเซีย : ริงกิต (MYR)","currency_name_eng":"MALAYSIA : RINGGIT (MYR)","buying_sight":"10.4093","buying_transfer":"10.4592","selling":"11.1620","flagPath":"/content/dam/bot/currencyflags/MYR.png","sortOrder":6},{"period":"23 Jul 2002","currency_id":"MYR","countryName":"Malaysia","currency_name_th":"มาเลเซีย : ริงกิต (MYR)","currency_name_eng":"MALAYSIA : RINGGIT (MYR)","buying_sight":"10.3801","buying_transfer":"10.4307","selling":"11.0366","flagPath":"/content/dam/bot/currencyflags/MYR.png","sortOrder":6},{"period":"22 Jul 2002","currency_id":"MYR","countryName":"Malaysia","currency_name_th":"มาเลเซีย : ริงกิต (MYR)","currency_name_eng":"MALAYSIA : RINGGIT (MYR)","buying_sight":"10.3474","buying_transfer":"10.4165","selling":"10.8395","flagPath":"/content/dam/bot/currencyflags/MYR.png","sortOrder":6},{"period":"19 Jul 2002","currency_id":"MYR","countryName":"Malaysia","currency_name_th":"มาเลเซีย : ริงกิต (MYR)","currency_name_eng":"MALAYSIA : RINGGIT (MYR)","buying_sight":"10.3175","buying_transfer":"10.3846","selling":"10.9293","flagPath":"/content/dam/bot/currencyflags/MYR.png","sortOrder":6},{"period":"18 Jul 2002","currency_id":"MYR","countryName":"Malaysia","currency_name_th":"มาเลเซีย : ริงกิต (MYR)","currency_name_eng":"MALAYSIA : RINGGIT (MYR)","buying_sight":"10.3504","buying_transfer":"10.4182","selling":"10.9047","flagPath":"/content/dam/bot/currencyflags/MYR.png","sortOrder":6},{"period":"17 Jul 2002","currency_id":"MYR","countryName":"Malaysia","currency_name_th":"มาเลเซีย : ริงกิต (MYR)","currency_name_eng":"MALAYSIA : RINGGIT (MYR)","buying_sight":"10.2504","buying_transfer":"10.3056","selling":"10.9707","flagPath":"/content/dam/bot/currencyflags/MYR.png","sortOrder":6},{"period":"16 Jul 2002","currency_id":"MYR","countryName":"Malaysia","currency_name_th":"มาเลเซีย : ริงกิต (MYR)","currency_name_eng":"MALAYSIA : RINGGIT (MYR)","buying_sight":"10.3658","buying_transfer":"10.4358","selling":"10.9642","flagPath":"/content/dam/bot/currencyflags/MYR.png","sortOrder":6},{"period":"15 Jul 2002","currency_id":"MYR","countryName":"Malaysia","currency_name_th":"มาเลเซีย : ริงกิต (MYR)","currency_name_eng":"MALAYSIA : RINGGIT (MYR)","buying_sight":"10.4141","buying_transfer":"10.4758","selling":"11.0801","flagPath":"/content/dam/bot/currencyflags/MYR.png","sortOrder":6},{"period":"12 Jul 2002","currency_id":"MYR","countryName":"Malaysia","currency_name_th":"มาเลเซีย : ริงกิต (MYR)","currency_name_eng":"MALAYSIA : RINGGIT (MYR)","buying_sight":"10.5445","buying_transfer":"10.6158","selling":"11.1133","flagPath":"/content/dam/bot/currencyflags/MYR.png","sortOrder":6},{"period":"11 Jul 2002","currency_id":"MYR","countryName":"Malaysia","currency_name_th":"มาเลเซีย : ริงกิต (MYR)","currency_name_eng":"MALAYSIA : RINGGIT (MYR)","buying_sight":"10.5409","buying_transfer":"10.5993","selling":"11.0532","flagPath":"/content/dam/bot/currencyflags/MYR.png","sortOrder":6},{"period":"10 Jul 2002","currency_id":"MYR","countryName":"Malaysia","currency_name_th":"มาเลเซีย : ริงกิต (MYR)","currency_name_eng":"MALAYSIA : RINGGIT (MYR)","buying_sight":"10.5609","buying_transfer":"10.6205","selling":"11.0724","flagPath":"/content/dam/bot/currencyflags/MYR.png","sortOrder":6},{"period":"09 Jul 2002","currency_id":"MYR","countryName":"Malaysia","currency_name_th":"มาเลเซีย : ริงกิต (MYR)","currency_name_eng":"MALAYSIA : RINGGIT (MYR)","buying_sight":"10.5759","buying_transfer":"10.6449","selling":"11.1441","flagPath":"/content/dam/bot/currencyflags/MYR.png","sortOrder":6},{"period":"08 Jul 2002","currency_id":"MYR","countryName":"Malaysia","currency_name_th":"มาเลเซีย : ริงกิต (MYR)","currency_name_eng":"MALAYSIA : RINGGIT (MYR)","buying_sight":"10.6128","buying_transfer":"10.6826","selling":"11.1836","flagPath":"/content/dam/bot/currencyflags/MYR.png","sortOrder":6},{"period":"05 Jul 2002","currency_id":"MYR","countryName":"Malaysia","currency_name_th":"มาเลเซีย : ริงกิต (MYR)","currency_name_eng":"MALAYSIA : RINGGIT (MYR)","buying_sight":"10.6346","buying_transfer":"10.7040","selling":"11.2053","flagPath":"/content/dam/bot/currencyflags/MYR.png","sortOrder":6},{"period":"04 Jul 2002","currency_id":"MYR","countryName":"Malaysia","currency_name_th":"มาเลเซีย : ริงกิต (MYR)","currency_name_eng":"MALAYSIA : RINGGIT (MYR)","buying_sight":"10.6334","buying_transfer":"10.7037","selling":"11.2043","flagPath":"/content/dam/bot/currencyflags/MYR.png","sortOrder":6},{"period":"03 Jul 2002","currency_id":"MYR","countryName":"Malaysia","currency_name_th":"มาเลเซีย : ริงกิต (MYR)","currency_name_eng":"MALAYSIA : RINGGIT (MYR)","buying_sight":"10.6656","buying_transfer":"10.7397","selling":"11.1731","flagPath":"/content/dam/bot/currencyflags/MYR.png","sortOrder":6},{"period":"02 Jul 2002","currency_id":"MYR","countryName":"Malaysia","currency_name_th":"มาเลเซีย : ริงกิต (MYR)","currency_name_eng":"MALAYSIA : RINGGIT (MYR)","buying_sight":"10.6116","buying_transfer":"10.6808","selling":"11.1817","flagPath":"/content/dam/bot/currencyflags/MYR.png","sortOrder":6},{"period":"28 Jun 2002","currency_id":"MYR","countryName":"Malaysia","currency_name_th":"มาเลเซีย : ริงกิต (MYR)","currency_name_eng":"MALAYSIA : RINGGIT (MYR)","buying_sight":"10.6292","buying_transfer":"10.6998","selling":"11.1976","flagPath":"/content/dam/bot/currencyflags/MYR.png","sortOrder":6},{"period":"27 Jun 2002","currency_id":"MYR","countryName":"Malaysia","currency_name_th":"มาเลเซีย : ริงกิต (MYR)","currency_name_eng":"MALAYSIA : RINGGIT (MYR)","buying_sight":"10.7396","buying_transfer":"10.8124","selling":"11.1527","flagPath":"/content/dam/bot/currencyflags/MYR.png","sortOrder":6},{"period":"26 Jun 2002","currency_id":"MYR","countryName":"Malaysia","currency_name_th":"มาเลเซีย : ริงกิต (MYR)","currency_name_eng":"MALAYSIA : RINGGIT (MYR)","buying_sight":"10.6782","buying_transfer":"10.7471","selling":"11.2473","flagPath":"/content/dam/bot/currencyflags/MYR.png","sortOrder":6},{"period":"25 Jun 2002","currency_id":"MYR","countryName":"Malaysia","currency_name_th":"มาเลเซีย : ริงกิต (MYR)","currency_name_eng":"MALAYSIA : RINGGIT (MYR)","buying_sight":"10.7407","buying_transfer":"10.8129","selling":"11.2498","flagPath":"/content/dam/bot/currencyflags/MYR.png","sortOrder":6},{"period":"24 Jun 2002","currency_id":"MYR","countryName":"Malaysia","currency_name_th":"มาเลเซีย : ริงกิต (MYR)","currency_name_eng":"MALAYSIA : RINGGIT (MYR)","buying_sight":"10.6995","buying_transfer":"10.7678","selling":"11.3181","flagPath":"/content/dam/bot/currencyflags/MYR.png","sortOrder":6},{"period":"21 Jun 2002","currency_id":"MYR","countryName":"Malaysia","currency_name_th":"มาเลเซีย : ริงกิต (MYR)","currency_name_eng":"MALAYSIA : RINGGIT (MYR)","buying_sight":"10.7436","buying_transfer":"10.8139","selling":"11.3198","flagPath":"/content/dam/bot/currencyflags/MYR.png","sortOrder":6},{"period":"20 Jun 2002","currency_id":"MYR","countryName":"Malaysia","currency_name_th":"มาเลเซีย : ริงกิต (MYR)","currency_name_eng":"MALAYSIA : RINGGIT (MYR)","buying_sight":"10.7931","buying_transfer":"10.8660","selling":"11.3049","flagPath":"/content/dam/bot/currencyflags/MYR.png","sortOrder":6},{"period":"19 Jun 2002","currency_id":"MYR","countryName":"Malaysia","currency_name_th":"มาเลเซีย : ริงกิต (MYR)","currency_name_eng":"MALAYSIA : RINGGIT (MYR)","buying_sight":"10.7743","buying_transfer":"10.8442","selling":"11.3517","flagPath":"/content/dam/bot/currencyflags/MYR.png","sortOrder":6},{"period":"18 Jun 2002","currency_id":"MYR","countryName":"Malaysia","currency_name_th":"มาเลเซีย : ริงกิต (MYR)","currency_name_eng":"MALAYSIA : RINGGIT (MYR)","buying_sight":"10.8137","buying_transfer":"10.8871","selling":"11.3266","flagPath":"/content/dam/bot/currencyflags/MYR.png","sortOrder":6},{"period":"17 Jun 2002","currency_id":"MYR","countryName":"Malaysia","currency_name_th":"มาเลเซีย : ริงกิต (MYR)","currency_name_eng":"MALAYSIA : RINGGIT (MYR)","buying_sight":"10.7944","buying_transfer":"10.8652","selling":"11.3711","flagPath":"/content/dam/bot/currencyflags/MYR.png","sortOrder":6},{"period":"14 Jun 2002","currency_id":"MYR","countryName":"Malaysia","currency_name_th":"มาเลเซีย : ริงกิต (MYR)","currency_name_eng":"MALAYSIA : RINGGIT (MYR)","buying_sight":"10.8590","buying_transfer":"10.9331","selling":"11.2766","flagPath":"/content/dam/bot/currencyflags/MYR.png","sortOrder":6},{"period":"13 Jun 2002","currency_id":"MYR","countryName":"Malaysia","currency_name_th":"มาเลเซีย : ริงกิต (MYR)","currency_name_eng":"MALAYSIA : RINGGIT (MYR)","buying_sight":"10.8108","buying_transfer":"10.8807","selling":"11.3896","flagPath":"/content/dam/bot/currencyflags/MYR.png","sortOrder":6},{"period":"12 Jun 2002","currency_id":"MYR","countryName":"Malaysia","currency_name_th":"มาเลเซีย : ริงกิต (MYR)","currency_name_eng":"MALAYSIA : RINGGIT (MYR)","buying_sight":"10.8571","buying_transfer":"10.9306","selling":"11.3713","flagPath":"/content/dam/bot/currencyflags/MYR.png","sortOrder":6},{"period":"11 Jun 2002","currency_id":"MYR","countryName":"Malaysia","currency_name_th":"มาเลเซีย : ริงกิต (MYR)","currency_name_eng":"MALAYSIA : RINGGIT (MYR)","buying_sight":"10.8520","buying_transfer":"10.9241","selling":"11.3645","flagPath":"/content/dam/bot/currencyflags/MYR.png","sortOrder":6},{"period":"10 Jun 2002","currency_id":"MYR","countryName":"Malaysia","currency_name_th":"มาเลเซีย : ริงกิต (MYR)","currency_name_eng":"MALAYSIA : RINGGIT (MYR)","buying_sight":"10.8785","buying_transfer":"10.9518","selling":"11.3931","flagPath":"/content/dam/bot/currencyflags/MYR.png","sortOrder":6},{"period":"07 Jun 2002","currency_id":"MYR","countryName":"Malaysia","currency_name_th":"มาเลเซีย : ริงกิต (MYR)","currency_name_eng":"MALAYSIA : RINGGIT (MYR)","buying_sight":"10.8579","buying_transfer":"10.9299","selling":"11.4403","flagPath":"/content/dam/bot/currencyflags/MYR.png","sortOrder":6},{"period":"06 Jun 2002","currency_id":"MYR","countryName":"Malaysia","currency_name_th":"มาเลเซีย : ริงกิต (MYR)","currency_name_eng":"MALAYSIA : RINGGIT (MYR)","buying_sight":"10.8590","buying_transfer":"10.9302","selling":"11.4408","flagPath":"/content/dam/bot/currencyflags/MYR.png","sortOrder":6},{"period":"05 Jun 2002","currency_id":"MYR","countryName":"Malaysia","currency_name_th":"มาเลเซีย : ริงกิต (MYR)","currency_name_eng":"MALAYSIA : RINGGIT (MYR)","buying_sight":"10.8259","buying_transfer":"10.8927","selling":"11.4500","flagPath":"/content/dam/bot/currencyflags/MYR.png","sortOrder":6},{"period":"04 Jun 2002","currency_id":"MYR","countryName":"Malaysia","currency_name_th":"มาเลเซีย : ริงกิต (MYR)","currency_name_eng":"MALAYSIA : RINGGIT (MYR)","buying_sight":"10.8238","buying_transfer":"10.8942","selling":"11.4036","flagPath":"/content/dam/bot/currencyflags/MYR.png","sortOrder":6},{"period":"03 Jun 2002","currency_id":"MYR","countryName":"Malaysia","currency_name_th":"มาเลเซีย : ริงกิต (MYR)","currency_name_eng":"MALAYSIA : RINGGIT (MYR)","buying_sight":"10.8544","buying_transfer":"10.9273","selling":"11.4335","flagPath":"/content/dam/bot/currencyflags/MYR.png","sortOrder":6},{"period":"31 May 2002","currency_id":"MYR","countryName":"Malaysia","currency_name_th":"มาเลเซีย : ริงกิต (MYR)","currency_name_eng":"MALAYSIA : RINGGIT (MYR)","buying_sight":"10.8431","buying_transfer":"10.9141","selling":"11.4224","flagPath":"/content/dam/bot/currencyflags/MYR.png","sortOrder":6},{"period":"30 May 2002","currency_id":"MYR","countryName":"Malaysia","currency_name_th":"มาเลเซีย : ริงกิต (MYR)","currency_name_eng":"MALAYSIA : RINGGIT (MYR)","buying_sight":"10.8822","buying_transfer":"10.9565","selling":"11.3978","flagPath":"/content/dam/bot/currencyflags/MYR.png","sortOrder":6},{"period":"29 May 2002","currency_id":"MYR","countryName":"Malaysia","currency_name_th":"มาเลเซีย : ริงกิต (MYR)","currency_name_eng":"MALAYSIA : RINGGIT (MYR)","buying_sight":"10.8802","buying_transfer":"10.9515","selling":"11.4633","flagPath":"/content/dam/bot/currencyflags/MYR.png","sortOrder":6},{"period":"28 May 2002","currency_id":"MYR","countryName":"Malaysia","currency_name_th":"มาเลเซีย : ริงกิต (MYR)","currency_name_eng":"MALAYSIA : RINGGIT (MYR)","buying_sight":"10.9164","buying_transfer":"10.9873","selling":"11.5005","flagPath":"/content/dam/bot/currencyflags/MYR.png","sortOrder":6},{"period":"24 May 2002","currency_id":"MYR","countryName":"Malaysia","currency_name_th":"มาเลเซีย : ริงกิต (MYR)","currency_name_eng":"MALAYSIA : RINGGIT (MYR)","buying_sight":"10.9544","buying_transfer":"11.0250","selling":"11.5396","flagPath":"/content/dam/bot/currencyflags/MYR.png","sortOrder":6},{"period":"23 May 2002","currency_id":"MYR","countryName":"Malaysia","currency_name_th":"มาเลเซีย : ริงกิต (MYR)","currency_name_eng":"MALAYSIA : RINGGIT (MYR)","buying_sight":"10.9591","buying_transfer":"11.0321","selling":"11.5469","flagPath":"/content/dam/bot/currencyflags/MYR.png","sortOrder":6},{"period":"22 May 2002","currency_id":"MYR","countryName":"Malaysia","currency_name_th":"มาเลเซีย : ริงกิต (MYR)","currency_name_eng":"MALAYSIA : RINGGIT (MYR)","buying_sight":"10.9001","buying_transfer":"10.9652","selling":"11.5228","flagPath":"/content/dam/bot/currencyflags/MYR.png","sortOrder":6},{"period":"21 May 2002","currency_id":"MYR","countryName":"Malaysia","currency_name_th":"มาเลเซีย : ริงกิต (MYR)","currency_name_eng":"MALAYSIA : RINGGIT (MYR)","buying_sight":"10.9121","buying_transfer":"10.9836","selling":"11.4967","flagPath":"/content/dam/bot/currencyflags/MYR.png","sortOrder":6},{"period":"20 May 2002","currency_id":"MYR","countryName":"Malaysia","currency_name_th":"มาเลเซีย : ริงกิต (MYR)","currency_name_eng":"MALAYSIA : RINGGIT (MYR)","buying_sight":"10.9180","buying_transfer":"10.9924","selling":"11.4362","flagPath":"/content/dam/bot/currencyflags/MYR.png","sortOrder":6},{"period":"17 May 2002","currency_id":"MYR","countryName":"Malaysia","currency_name_th":"มาเลเซีย : ริงกิต (MYR)","currency_name_eng":"MALAYSIA : RINGGIT (MYR)","buying_sight":"10.9297","buying_transfer":"11.0010","selling":"11.5150","flagPath":"/content/dam/bot/currencyflags/MYR.png","sortOrder":6},{"period":"16 May 2002","currency_id":"MYR","countryName":"Malaysia","currency_name_th":"มาเลเซีย : ริงกิต (MYR)","currency_name_eng":"MALAYSIA : RINGGIT (MYR)","buying_sight":"10.9904","buying_transfer":"11.0634","selling":"11.5092","flagPath":"/content/dam/bot/currencyflags/MYR.png","sortOrder":6},{"period":"15 May 2002","currency_id":"MYR","countryName":"Malaysia","currency_name_th":"มาเลเซีย : ริงกิต (MYR)","currency_name_eng":"MALAYSIA : RINGGIT (MYR)","buying_sight":"10.9946","buying_transfer":"11.0677","selling":"11.5132","flagPath":"/content/dam/bot/currencyflags/MYR.png","sortOrder":6},{"period":"14 May 2002","currency_id":"MYR","countryName":"Malaysia","currency_name_th":"มาเลเซีย : ริงกิต (MYR)","currency_name_eng":"MALAYSIA : RINGGIT (MYR)","buying_sight":"10.9880","buying_transfer":"11.0613","selling":"11.5068","flagPath":"/content/dam/bot/currencyflags/MYR.png","sortOrder":6},{"period":"13 May 2002","currency_id":"MYR","countryName":"Malaysia","currency_name_th":"มาเลเซีย : ริงกิต (MYR)","currency_name_eng":"MALAYSIA : RINGGIT (MYR)","buying_sight":"11.0278","buying_transfer":"11.1016","selling":"11.4489","flagPath":"/content/dam/bot/currencyflags/MYR.png","sortOrder":6},{"period":"10 May 2002","currency_id":"MYR","countryName":"Malaysia","currency_name_th":"มาเลเซีย : ริงกิต (MYR)","currency_name_eng":"MALAYSIA : RINGGIT (MYR)","buying_sight":"10.9764","buying_transfer":"11.0475","selling":"11.5635","flagPath":"/content/dam/bot/currencyflags/MYR.png","sortOrder":6},{"period":"09 May 2002","currency_id":"MYR","countryName":"Malaysia","currency_name_th":"มาเลเซีย : ริงกิต (MYR)","currency_name_eng":"MALAYSIA : RINGGIT (MYR)","buying_sight":"11.0067","buying_transfer":"11.0796","selling":"11.5256","flagPath":"/content/dam/bot/currencyflags/MYR.png","sortOrder":6},{"period":"08 May 2002","currency_id":"MYR","countryName":"Malaysia","currency_name_th":"มาเลเซีย : ริงกิต (MYR)","currency_name_eng":"MALAYSIA : RINGGIT (MYR)","buying_sight":"10.9748","buying_transfer":"11.0461","selling":"11.5620","flagPath":"/content/dam/bot/currencyflags/MYR.png","sortOrder":6},{"period":"07 May 2002","currency_id":"MYR","countryName":"Malaysia","currency_name_th":"มาเลเซีย : ริงกิต (MYR)","currency_name_eng":"MALAYSIA : RINGGIT (MYR)","buying_sight":"10.9956","buying_transfer":"11.0690","selling":"11.5144","flagPath":"/content/dam/bot/currencyflags/MYR.png","sortOrder":6},{"period":"03 May 2002","currency_id":"MYR","countryName":"Malaysia","currency_name_th":"มาเลเซีย : ริงกิต (MYR)","currency_name_eng":"MALAYSIA : RINGGIT (MYR)","buying_sight":"11.0289","buying_transfer":"11.1005","selling":"11.6158","flagPath":"/content/dam/bot/currencyflags/MYR.png","sortOrder":6},{"period":"02 May 2002","currency_id":"MYR","countryName":"Malaysia","currency_name_th":"มาเลเซีย : ริงกิต (MYR)","currency_name_eng":"MALAYSIA : RINGGIT (MYR)","buying_sight":"11.0339","buying_transfer":"11.1048","selling":"11.6196","flagPath":"/content/dam/bot/currencyflags/MYR.png","sortOrder":6},{"period":"30 Apr 2002","currency_id":"MYR","countryName":"Malaysia","currency_name_th":"มาเลเซีย : ริงกิต (MYR)","currency_name_eng":"MALAYSIA : RINGGIT (MYR)","buying_sight":"11.0889","buying_transfer":"11.1624","selling":"11.6114","flagPath":"/content/dam/bot/currencyflags/MYR.png","sortOrder":6},{"period":"29 Apr 2002","currency_id":"MYR","countryName":"Malaysia","currency_name_th":"มาเลเซีย : ริงกิต (MYR)","currency_name_eng":"MALAYSIA : RINGGIT (MYR)","buying_sight":"11.0498","buying_transfer":"11.1211","selling":"11.6392","flagPath":"/content/dam/bot/currencyflags/MYR.png","sortOrder":6},{"period":"26 Apr 2002","currency_id":"MYR","countryName":"Malaysia","currency_name_th":"มาเลเซีย : ริงกิต (MYR)","currency_name_eng":"MALAYSIA : RINGGIT (MYR)","buying_sight":"11.0540","buying_transfer":"11.1258","selling":"11.6449","flagPath":"/content/dam/bot/currencyflags/MYR.png","sortOrder":6},{"period":"25 Apr 2002","currency_id":"MYR","countryName":"Malaysia","currency_name_th":"มาเลเซีย : ริงกิต (MYR)","currency_name_eng":"MALAYSIA : RINGGIT (MYR)","buying_sight":"11.0570","buying_transfer":"11.1302","selling":"11.6485","flagPath":"/content/dam/bot/currencyflags/MYR.png","sortOrder":6},{"period":"24 Apr 2002","currency_id":"MYR","countryName":"Malaysia","currency_name_th":"มาเลเซีย : ริงกิต (MYR)","currency_name_eng":"MALAYSIA : RINGGIT (MYR)","buying_sight":"11.1396","buying_transfer":"11.2019","selling":"11.6111","flagPath":"/content/dam/bot/currencyflags/MYR.png","sortOrder":6},{"period":"23 Apr 2002","currency_id":"MYR","countryName":"Malaysia","currency_name_th":"มาเลเซีย : ริงกิต (MYR)","currency_name_eng":"MALAYSIA : RINGGIT (MYR)","buying_sight":"11.0685","buying_transfer":"11.1396","selling":"11.6573","flagPath":"/content/dam/bot/currencyflags/MYR.png","sortOrder":6},{"period":"22 Apr 2002","currency_id":"MYR","countryName":"Malaysia","currency_name_th":"มาเลเซีย : ริงกิต (MYR)","currency_name_eng":"MALAYSIA : RINGGIT (MYR)","buying_sight":"11.0631","buying_transfer":"11.1345","selling":"11.6540","flagPath":"/content/dam/bot/currencyflags/MYR.png","sortOrder":6},{"period":"19 Apr 2002","currency_id":"MYR","countryName":"Malaysia","currency_name_th":"มาเลเซีย : ริงกิต (MYR)","currency_name_eng":"MALAYSIA : RINGGIT (MYR)","buying_sight":"11.0435","buying_transfer":"11.1120","selling":"11.6821","flagPath":"/content/dam/bot/currencyflags/MYR.png","sortOrder":6},{"period":"18 Apr 2002","currency_id":"MYR","countryName":"Malaysia","currency_name_th":"มาเลเซีย : ริงกิต (MYR)","currency_name_eng":"MALAYSIA : RINGGIT (MYR)","buying_sight":"11.1050","buying_transfer":"11.1804","selling":"11.6301","flagPath":"/content/dam/bot/currencyflags/MYR.png","sortOrder":6},{"period":"17 Apr 2002","currency_id":"MYR","countryName":"Malaysia","currency_name_th":"มาเลเซีย : ริงกิต (MYR)","currency_name_eng":"MALAYSIA : RINGGIT (MYR)","buying_sight":"11.0975","buying_transfer":"11.1697","selling":"11.6908","flagPath":"/content/dam/bot/currencyflags/MYR.png","sortOrder":6},{"period":"12 Apr 2002","currency_id":"MYR","countryName":"Malaysia","currency_name_th":"มาเลเซีย : ริงกิต (MYR)","currency_name_eng":"MALAYSIA : RINGGIT (MYR)","buying_sight":"11.1394","buying_transfer":"11.2125","selling":"11.7332","flagPath":"/content/dam/bot/currencyflags/MYR.png","sortOrder":6},{"period":"11 Apr 2002","currency_id":"MYR","countryName":"Malaysia","currency_name_th":"มาเลเซีย : ริงกิต (MYR)","currency_name_eng":"MALAYSIA : RINGGIT (MYR)","buying_sight":"11.0985","buying_transfer":"11.1667","selling":"11.7396","flagPath":"/content/dam/bot/currencyflags/MYR.png","sortOrder":6},{"period":"10 Apr 2002","currency_id":"MYR","countryName":"Malaysia","currency_name_th":"มาเลเซีย : ริงกิต (MYR)","currency_name_eng":"MALAYSIA : RINGGIT (MYR)","buying_sight":"11.1457","buying_transfer":"11.2203","selling":"11.6717","flagPath":"/content/dam/bot/currencyflags/MYR.png","sortOrder":6},{"period":"09 Apr 2002","currency_id":"MYR","countryName":"Malaysia","currency_name_th":"มาเลเซีย : ริงกิต (MYR)","currency_name_eng":"MALAYSIA : RINGGIT (MYR)","buying_sight":"11.1318","buying_transfer":"11.2040","selling":"11.7256","flagPath":"/content/dam/bot/currencyflags/MYR.png","sortOrder":6},{"period":"05 Apr 2002","currency_id":"MYR","countryName":"Malaysia","currency_name_th":"มาเลเซีย : ริงกิต (MYR)","currency_name_eng":"MALAYSIA : RINGGIT (MYR)","buying_sight":"11.1423","buying_transfer":"11.2146","selling":"11.7494","flagPath":"/content/dam/bot/currencyflags/MYR.png","sortOrder":6},{"period":"04 Apr 2002","currency_id":"MYR","countryName":"Malaysia","currency_name_th":"มาเลเซีย : ริงกิต (MYR)","currency_name_eng":"MALAYSIA : RINGGIT (MYR)","buying_sight":"11.1546","buying_transfer":"11.2251","selling":"11.7525","flagPath":"/content/dam/bot/currencyflags/MYR.png","sortOrder":6},{"period":"03 Apr 2002","currency_id":"MYR","countryName":"Malaysia","currency_name_th":"มาเลเซีย : ริงกิต (MYR)","currency_name_eng":"MALAYSIA : RINGGIT (MYR)","buying_sight":"11.1853","buying_transfer":"11.2592","selling":"11.7791","flagPath":"/content/dam/bot/currencyflags/MYR.png","sortOrder":6},{"period":"02 Apr 2002","currency_id":"MYR","countryName":"Malaysia","currency_name_th":"มาเลเซีย : ริงกิต (MYR)","currency_name_eng":"MALAYSIA : RINGGIT (MYR)","buying_sight":"11.1392","buying_transfer":"11.2039","selling":"11.7704","flagPath":"/content/dam/bot/currencyflags/MYR.png","sortOrder":6},{"period":"01 Apr 2002","currency_id":"MYR","countryName":"Malaysia","currency_name_th":"มาเลเซีย : ริงกิต (MYR)","currency_name_eng":"MALAYSIA : RINGGIT (MYR)","buying_sight":"11.1306","buying_transfer":"11.2026","selling":"11.7138","flagPath":"/content/dam/bot/currencyflags/MYR.png","sortOrder":6},{"period":"29 Mar 2002","currency_id":"MYR","countryName":"Malaysia","currency_name_th":"มาเลเซีย : ริงกิต (MYR)","currency_name_eng":"MALAYSIA : RINGGIT (MYR)","buying_sight":"11.1340","buying_transfer":"11.2065","selling":"11.7142","flagPath":"/content/dam/bot/currencyflags/MYR.png","sortOrder":6},{"period":"28 Mar 2002","currency_id":"MYR","countryName":"Malaysia","currency_name_th":"มาเลเซีย : ริงกิต (MYR)","currency_name_eng":"MALAYSIA : RINGGIT (MYR)","buying_sight":"11.0582","buying_transfer":"11.1248","selling":"11.6951","flagPath":"/content/dam/bot/currencyflags/MYR.png","sortOrder":6},{"period":"27 Mar 2002","currency_id":"MYR","countryName":"Malaysia","currency_name_th":"มาเลเซีย : ริงกิต (MYR)","currency_name_eng":"MALAYSIA : RINGGIT (MYR)","buying_sight":"11.0782","buying_transfer":"11.1493","selling":"11.6696","flagPath":"/content/dam/bot/currencyflags/MYR.png","sortOrder":6},{"period":"26 Mar 2002","currency_id":"MYR","countryName":"Malaysia","currency_name_th":"มาเลเซีย : ริงกิต (MYR)","currency_name_eng":"MALAYSIA : RINGGIT (MYR)","buying_sight":"11.1292","buying_transfer":"11.2030","selling":"11.6493","flagPath":"/content/dam/bot/currencyflags/MYR.png","sortOrder":6},{"period":"25 Mar 2002","currency_id":"MYR","countryName":"Malaysia","currency_name_th":"มาเลเซีย : ริงกิต (MYR)","currency_name_eng":"MALAYSIA : RINGGIT (MYR)","buying_sight":"11.1568","buying_transfer":"11.2200","selling":"11.6275","flagPath":"/content/dam/bot/currencyflags/MYR.png","sortOrder":6},{"period":"22 Mar 2002","currency_id":"MYR","countryName":"Malaysia","currency_name_th":"มาเลเซีย : ริงกิต (MYR)","currency_name_eng":"MALAYSIA : RINGGIT (MYR)","buying_sight":"11.1166","buying_transfer":"11.1908","selling":"11.6384","flagPath":"/content/dam/bot/currencyflags/MYR.png","sortOrder":6},{"period":"21 Mar 2002","currency_id":"MYR","countryName":"Malaysia","currency_name_th":"มาเลเซีย : ริงกิต (MYR)","currency_name_eng":"MALAYSIA : RINGGIT (MYR)","buying_sight":"11.0832","buying_transfer":"11.1543","selling":"11.6704","flagPath":"/content/dam/bot/currencyflags/MYR.png","sortOrder":6},{"period":"20 Mar 2002","currency_id":"MYR","countryName":"Malaysia","currency_name_th":"มาเลเซีย : ริงกิต (MYR)","currency_name_eng":"MALAYSIA : RINGGIT (MYR)","buying_sight":"11.1286","buying_transfer":"11.2035","selling":"11.6647","flagPath":"/content/dam/bot/currencyflags/MYR.png","sortOrder":6},{"period":"19 Mar 2002","currency_id":"MYR","countryName":"Malaysia","currency_name_th":"มาเลเซีย : ริงกิต (MYR)","currency_name_eng":"MALAYSIA : RINGGIT (MYR)","buying_sight":"11.1341","buying_transfer":"11.2081","selling":"11.6594","flagPath":"/content/dam/bot/currencyflags/MYR.png","sortOrder":6},{"period":"18 Mar 2002","currency_id":"MYR","countryName":"Malaysia","currency_name_th":"มาเลเซีย : ริงกิต (MYR)","currency_name_eng":"MALAYSIA : RINGGIT (MYR)","buying_sight":"11.0999","buying_transfer":"11.1726","selling":"11.6222","flagPath":"/content/dam/bot/currencyflags/MYR.png","sortOrder":6},{"period":"15 Mar 2002","currency_id":"MYR","countryName":"Malaysia","currency_name_th":"มาเลเซีย : ริงกิต (MYR)","currency_name_eng":"MALAYSIA : RINGGIT (MYR)","buying_sight":"11.0561","buying_transfer":"11.1284","selling":"11.6451","flagPath":"/content/dam/bot/currencyflags/MYR.png","sortOrder":6},{"period":"14 Mar 2002","currency_id":"MYR","countryName":"Malaysia","currency_name_th":"มาเลเซีย : ริงกิต (MYR)","currency_name_eng":"MALAYSIA : RINGGIT (MYR)","buying_sight":"11.1267","buying_transfer":"11.1871","selling":"11.5973","flagPath":"/content/dam/bot/currencyflags/MYR.png","sortOrder":6},{"period":"13 Mar 2002","currency_id":"MYR","countryName":"Malaysia","currency_name_th":"มาเลเซีย : ริงกิต (MYR)","currency_name_eng":"MALAYSIA : RINGGIT (MYR)","buying_sight":"11.1271","buying_transfer":"11.2014","selling":"11.5522","flagPath":"/content/dam/bot/currencyflags/MYR.png","sortOrder":6},{"period":"12 Mar 2002","currency_id":"MYR","countryName":"Malaysia","currency_name_th":"มาเลเซีย : ริงกิต (MYR)","currency_name_eng":"MALAYSIA : RINGGIT (MYR)","buying_sight":"11.0844","buying_transfer":"11.1467","selling":"11.6198","flagPath":"/content/dam/bot/currencyflags/MYR.png","sortOrder":6},{"period":"11 Mar 2002","currency_id":"MYR","countryName":"Malaysia","currency_name_th":"มาเลเซีย : ริงกิต (MYR)","currency_name_eng":"MALAYSIA : RINGGIT (MYR)","buying_sight":"11.0686","buying_transfer":"11.1368","selling":"11.7072","flagPath":"/content/dam/bot/currencyflags/MYR.png","sortOrder":6},{"period":"08 Mar 2002","currency_id":"MYR","countryName":"Malaysia","currency_name_th":"มาเลเซีย : ริงกิต (MYR)","currency_name_eng":"MALAYSIA : RINGGIT (MYR)","buying_sight":"11.0015","buying_transfer":"11.0569","selling":"11.6835","flagPath":"/content/dam/bot/currencyflags/MYR.png","sortOrder":6},{"period":"07 Mar 2002","currency_id":"MYR","countryName":"Malaysia","currency_name_th":"มาเลเซีย : ริงกิต (MYR)","currency_name_eng":"MALAYSIA : RINGGIT (MYR)","buying_sight":"11.1025","buying_transfer":"11.1731","selling":"11.6897","flagPath":"/content/dam/bot/currencyflags/MYR.png","sortOrder":6},{"period":"06 Mar 2002","currency_id":"MYR","countryName":"Malaysia","currency_name_th":"มาเลเซีย : ริงกิต (MYR)","currency_name_eng":"MALAYSIA : RINGGIT (MYR)","buying_sight":"11.2216","buying_transfer":"11.2974","selling":"11.6508","flagPath":"/content/dam/bot/currencyflags/MYR.png","sortOrder":6},{"period":"05 Mar 2002","currency_id":"MYR","countryName":"Malaysia","currency_name_th":"มาเลเซีย : ริงกิต (MYR)","currency_name_eng":"MALAYSIA : RINGGIT (MYR)","buying_sight":"11.1479","buying_transfer":"11.2181","selling":"11.7386","flagPath":"/content/dam/bot/currencyflags/MYR.png","sortOrder":6},{"period":"04 Mar 2002","currency_id":"MYR","countryName":"Malaysia","currency_name_th":"มาเลเซีย : ริงกิต (MYR)","currency_name_eng":"MALAYSIA : RINGGIT (MYR)","buying_sight":"11.1895","buying_transfer":"11.2648","selling":"11.7175","flagPath":"/content/dam/bot/currencyflags/MYR.png","sortOrder":6},{"period":"01 Mar 2002","currency_id":"MYR","countryName":"Malaysia","currency_name_th":"มาเลเซีย : ริงกิต (MYR)","currency_name_eng":"MALAYSIA : RINGGIT (MYR)","buying_sight":"11.1685","buying_transfer":"11.2403","selling":"11.7638","flagPath":"/content/dam/bot/currencyflags/MYR.png","sortOrder":6},{"period":"28 Feb 2002","currency_id":"MYR","countryName":"Malaysia","currency_name_th":"มาเลเซีย : ริงกิต (MYR)","currency_name_eng":"MALAYSIA : RINGGIT (MYR)","buying_sight":"11.1862","buying_transfer":"11.2242","selling":"11.8197","flagPath":"/content/dam/bot/currencyflags/MYR.png","sortOrder":6},{"period":"27 Feb 2002","currency_id":"MYR","countryName":"Malaysia","currency_name_th":"มาเลเซีย : ริงกิต (MYR)","currency_name_eng":"MALAYSIA : RINGGIT (MYR)","buying_sight":"11.2516","buying_transfer":"11.3256","selling":"11.7806","flagPath":"/content/dam/bot/currencyflags/MYR.png","sortOrder":6},{"period":"25 Feb 2002","currency_id":"MYR","countryName":"Malaysia","currency_name_th":"มาเลเซีย : ริงกิต (MYR)","currency_name_eng":"MALAYSIA : RINGGIT (MYR)","buying_sight":"11.2163","buying_transfer":"11.2891","selling":"11.8150","flagPath":"/content/dam/bot/currencyflags/MYR.png","sortOrder":6},{"period":"22 Feb 2002","currency_id":"MYR","countryName":"Malaysia","currency_name_th":"มาเลเซีย : ริงกิต (MYR)","currency_name_eng":"MALAYSIA : RINGGIT (MYR)","buying_sight":"11.1645","buying_transfer":"11.2509","selling":"11.8349","flagPath":"/content/dam/bot/currencyflags/MYR.png","sortOrder":6},{"period":"21 Feb 2002","currency_id":"MYR","countryName":"Malaysia","currency_name_th":"มาเลเซีย : ริงกิต (MYR)","currency_name_eng":"MALAYSIA : RINGGIT (MYR)","buying_sight":"11.1407","buying_transfer":"11.2272","selling":"11.8112","flagPath":"/content/dam/bot/currencyflags/MYR.png","sortOrder":6},{"period":"20 Feb 2002","currency_id":"MYR","countryName":"Malaysia","currency_name_th":"มาเลเซีย : ริงกิต (MYR)","currency_name_eng":"MALAYSIA : RINGGIT (MYR)","buying_sight":"11.1540","buying_transfer":"11.2491","selling":"11.7572","flagPath":"/content/dam/bot/currencyflags/MYR.png","sortOrder":6},{"period":"19 Feb 2002","currency_id":"MYR","countryName":"Malaysia","currency_name_th":"มาเลเซีย : ริงกิต (MYR)","currency_name_eng":"MALAYSIA : RINGGIT (MYR)","buying_sight":"11.1118","buying_transfer":"11.1997","selling":"11.7810","flagPath":"/content/dam/bot/currencyflags/MYR.png","sortOrder":6},{"period":"18 Feb 2002","currency_id":"MYR","countryName":"Malaysia","currency_name_th":"มาเลเซีย : ริงกิต (MYR)","currency_name_eng":"MALAYSIA : RINGGIT (MYR)","buying_sight":"11.1275","buying_transfer":"11.2241","selling":"11.7310","flagPath":"/content/dam/bot/currencyflags/MYR.png","sortOrder":6},{"period":"15 Feb 2002","currency_id":"MYR","countryName":"Malaysia","currency_name_th":"มาเลเซีย : ริงกิต (MYR)","currency_name_eng":"MALAYSIA : RINGGIT (MYR)","buying_sight":"11.0978","buying_transfer":"11.1854","selling":"11.7653","flagPath":"/content/dam/bot/currencyflags/MYR.png","sortOrder":6},{"period":"14 Feb 2002","currency_id":"MYR","countryName":"Malaysia","currency_name_th":"มาเลเซีย : ริงกิต (MYR)","currency_name_eng":"MALAYSIA : RINGGIT (MYR)","buying_sight":"11.1374","buying_transfer":"11.2261","selling":"11.8086","flagPath":"/content/dam/bot/currencyflags/MYR.png","sortOrder":6},{"period":"13 Feb 2002","currency_id":"MYR","countryName":"Malaysia","currency_name_th":"มาเลเซีย : ริงกิต (MYR)","currency_name_eng":"MALAYSIA : RINGGIT (MYR)","buying_sight":"11.1851","buying_transfer":"11.2805","selling":"11.7858","flagPath":"/content/dam/bot/currencyflags/MYR.png","sortOrder":6},{"period":"12 Feb 2002","currency_id":"MYR","countryName":"Malaysia","currency_name_th":"มาเลเซีย : ริงกิต (MYR)","currency_name_eng":"MALAYSIA : RINGGIT (MYR)","buying_sight":"11.2001","buying_transfer":"11.2946","selling":"11.8014","flagPath":"/content/dam/bot/currencyflags/MYR.png","sortOrder":6},{"period":"11 Feb 2002","currency_id":"MYR","countryName":"Malaysia","currency_name_th":"มาเลเซีย : ริงกิต (MYR)","currency_name_eng":"MALAYSIA : RINGGIT (MYR)","buying_sight":"11.2587","buying_transfer":"11.3600","selling":"11.7599","flagPath":"/content/dam/bot/currencyflags/MYR.png","sortOrder":6},{"period":"08 Feb 2002","currency_id":"MYR","countryName":"Malaysia","currency_name_th":"มาเลเซีย : ริงกิต (MYR)","currency_name_eng":"MALAYSIA : RINGGIT (MYR)","buying_sight":"11.2136","buying_transfer":"11.3067","selling":"11.8174","flagPath":"/content/dam/bot/currencyflags/MYR.png","sortOrder":6},{"period":"07 Feb 2002","currency_id":"MYR","countryName":"Malaysia","currency_name_th":"มาเลเซีย : ริงกิต (MYR)","currency_name_eng":"MALAYSIA : RINGGIT (MYR)","buying_sight":"11.1715","buying_transfer":"11.2537","selling":"11.8883","flagPath":"/content/dam/bot/currencyflags/MYR.png","sortOrder":6},{"period":"06 Feb 2002","currency_id":"MYR","countryName":"Malaysia","currency_name_th":"มาเลเซีย : ริงกิต (MYR)","currency_name_eng":"MALAYSIA : RINGGIT (MYR)","buying_sight":"11.2304","buying_transfer":"11.3268","selling":"11.8380","flagPath":"/content/dam/bot/currencyflags/MYR.png","sortOrder":6},{"period":"05 Feb 2002","currency_id":"MYR","countryName":"Malaysia","currency_name_th":"มาเลเซีย : ริงกิต (MYR)","currency_name_eng":"MALAYSIA : RINGGIT (MYR)","buying_sight":"11.1983","buying_transfer":"11.2863","selling":"11.8717","flagPath":"/content/dam/bot/currencyflags/MYR.png","sortOrder":6},{"period":"04 Feb 2002","currency_id":"MYR","countryName":"Malaysia","currency_name_th":"มาเลเซีย : ริงกิต (MYR)","currency_name_eng":"MALAYSIA : RINGGIT (MYR)","buying_sight":"11.2383","buying_transfer":"11.3313","selling":"11.8427","flagPath":"/content/dam/bot/currencyflags/MYR.png","sortOrder":6},{"period":"01 Feb 2002","currency_id":"MYR","countryName":"Malaysia","currency_name_th":"มาเลเซีย : ริงกิต (MYR)","currency_name_eng":"MALAYSIA : RINGGIT (MYR)","buying_sight":"11.2230","buying_transfer":"11.3139","selling":"11.9000","flagPath":"/content/dam/bot/currencyflags/MYR.png","sortOrder":6},{"period":"31 Jan 2002","currency_id":"MYR","countryName":"Malaysia","currency_name_th":"มาเลเซีย : ริงกิต (MYR)","currency_name_eng":"MALAYSIA : RINGGIT (MYR)","buying_sight":"11.1798","buying_transfer":"11.2624","selling":"11.9009","flagPath":"/content/dam/bot/currencyflags/MYR.png","sortOrder":6},{"period":"30 Jan 2002","currency_id":"MYR","countryName":"Malaysia","currency_name_th":"มาเลเซีย : ริงกิต (MYR)","currency_name_eng":"MALAYSIA : RINGGIT (MYR)","buying_sight":"11.2971","buying_transfer":"11.3973","selling":"11.7981","flagPath":"/content/dam/bot/currencyflags/MYR.png","sortOrder":6},{"period":"29 Jan 2002","currency_id":"MYR","countryName":"Malaysia","currency_name_th":"มาเลเซีย : ริงกิต (MYR)","currency_name_eng":"MALAYSIA : RINGGIT (MYR)","buying_sight":"11.1973","buying_transfer":"11.2806","selling":"11.9192","flagPath":"/content/dam/bot/currencyflags/MYR.png","sortOrder":6},{"period":"28 Jan 2002","currency_id":"MYR","countryName":"Malaysia","currency_name_th":"มาเลเซีย : ริงกิต (MYR)","currency_name_eng":"MALAYSIA : RINGGIT (MYR)","buying_sight":"11.2084","buying_transfer":"11.2899","selling":"11.9274","flagPath":"/content/dam/bot/currencyflags/MYR.png","sortOrder":6},{"period":"25 Jan 2002","currency_id":"MYR","countryName":"Malaysia","currency_name_th":"มาเลเซีย : ริงกิต (MYR)","currency_name_eng":"MALAYSIA : RINGGIT (MYR)","buying_sight":"11.2449","buying_transfer":"11.3341","selling":"11.9221","flagPath":"/content/dam/bot/currencyflags/MYR.png","sortOrder":6},{"period":"24 Jan 2002","currency_id":"MYR","countryName":"Malaysia","currency_name_th":"มาเลเซีย : ริงกิต (MYR)","currency_name_eng":"MALAYSIA : RINGGIT (MYR)","buying_sight":"11.2865","buying_transfer":"11.3823","selling":"11.8959","flagPath":"/content/dam/bot/currencyflags/MYR.png","sortOrder":6},{"period":"23 Jan 2002","currency_id":"MYR","countryName":"Malaysia","currency_name_th":"มาเลเซีย : ริงกิต (MYR)","currency_name_eng":"MALAYSIA : RINGGIT (MYR)","buying_sight":"11.2385","buying_transfer":"11.3217","selling":"11.9598","flagPath":"/content/dam/bot/currencyflags/MYR.png","sortOrder":6},{"period":"22 Jan 2002","currency_id":"MYR","countryName":"Malaysia","currency_name_th":"มาเลเซีย : ริงกิต (MYR)","currency_name_eng":"MALAYSIA : RINGGIT (MYR)","buying_sight":"11.1970","buying_transfer":"11.3029","selling":"11.9148","flagPath":"/content/dam/bot/currencyflags/MYR.png","sortOrder":6},{"period":"21 Jan 2002","currency_id":"MYR","countryName":"Malaysia","currency_name_th":"มาเลเซีย : ริงกิต (MYR)","currency_name_eng":"MALAYSIA : RINGGIT (MYR)","buying_sight":"11.1917","buying_transfer":"11.2803","selling":"11.8657","flagPath":"/content/dam/bot/currencyflags/MYR.png","sortOrder":6},{"period":"18 Jan 2002","currency_id":"MYR","countryName":"Malaysia","currency_name_th":"มาเลเซีย : ริงกิต (MYR)","currency_name_eng":"MALAYSIA : RINGGIT (MYR)","buying_sight":"11.2128","buying_transfer":"11.3083","selling":"11.8189","flagPath":"/content/dam/bot/currencyflags/MYR.png","sortOrder":6},{"period":"17 Jan 2002","currency_id":"MYR","countryName":"Malaysia","currency_name_th":"มาเลเซีย : ริงกิต (MYR)","currency_name_eng":"MALAYSIA : RINGGIT (MYR)","buying_sight":"11.1822","buying_transfer":"11.2707","selling":"11.8553","flagPath":"/content/dam/bot/currencyflags/MYR.png","sortOrder":6},{"period":"16 Jan 2002","currency_id":"MYR","countryName":"Malaysia","currency_name_th":"มาเลเซีย : ริงกิต (MYR)","currency_name_eng":"MALAYSIA : RINGGIT (MYR)","buying_sight":"11.1551","buying_transfer":"11.2364","selling":"11.8733","flagPath":"/content/dam/bot/currencyflags/MYR.png","sortOrder":6},{"period":"15 Jan 2002","currency_id":"MYR","countryName":"Malaysia","currency_name_th":"มาเลเซีย : ริงกิต (MYR)","currency_name_eng":"MALAYSIA : RINGGIT (MYR)","buying_sight":"11.1918","buying_transfer":"11.2799","selling":"11.8650","flagPath":"/content/dam/bot/currencyflags/MYR.png","sortOrder":6},{"period":"14 Jan 2002","currency_id":"MYR","countryName":"Malaysia","currency_name_th":"มาเลเซีย : ริงกิต (MYR)","currency_name_eng":"MALAYSIA : RINGGIT (MYR)","buying_sight":"11.1719","buying_transfer":"11.2534","selling":"11.8913","flagPath":"/content/dam/bot/currencyflags/MYR.png","sortOrder":6},{"period":"11 Jan 2002","currency_id":"MYR","countryName":"Malaysia","currency_name_th":"มาเลเซีย : ริงกิต (MYR)","currency_name_eng":"MALAYSIA : RINGGIT (MYR)","buying_sight":"11.2380","buying_transfer":"11.3341","selling":"11.8485","flagPath":"/content/dam/bot/currencyflags/MYR.png","sortOrder":6},{"period":"10 Jan 2002","currency_id":"MYR","countryName":"Malaysia","currency_name_th":"มาเลเซีย : ริงกิต (MYR)","currency_name_eng":"MALAYSIA : RINGGIT (MYR)","buying_sight":"11.2228","buying_transfer":"11.3127","selling":"11.8988","flagPath":"/content/dam/bot/currencyflags/MYR.png","sortOrder":6},{"period":"09 Jan 2002","currency_id":"MYR","countryName":"Malaysia","currency_name_th":"มาเลเซีย : ริงกิต (MYR)","currency_name_eng":"MALAYSIA : RINGGIT (MYR)","buying_sight":"11.2194","buying_transfer":"11.3027","selling":"11.9418","flagPath":"/content/dam/bot/currencyflags/MYR.png","sortOrder":6},{"period":"08 Jan 2002","currency_id":"MYR","countryName":"Malaysia","currency_name_th":"มาเลเซีย : ริงกิต (MYR)","currency_name_eng":"MALAYSIA : RINGGIT (MYR)","buying_sight":"11.1864","buying_transfer":"11.2654","selling":"11.8992","flagPath":"/content/dam/bot/currencyflags/MYR.png","sortOrder":6},{"period":"07 Jan 2002","currency_id":"MYR","countryName":"Malaysia","currency_name_th":"มาเลเซีย : ริงกิต (MYR)","currency_name_eng":"MALAYSIA : RINGGIT (MYR)","buying_sight":"11.1686","buying_transfer":"11.2570","selling":"11.8408","flagPath":"/content/dam/bot/currencyflags/MYR.png","sortOrder":6},{"period":"04 Jan 2002","currency_id":"MYR","countryName":"Malaysia","currency_name_th":"มาเลเซีย : ริงกิต (MYR)","currency_name_eng":"MALAYSIA : RINGGIT (MYR)","buying_sight":"11.2082","buying_transfer":"11.2974","selling":"11.8824","flagPath":"/content/dam/bot/currencyflags/MYR.png","sortOrder":6},{"period":"03 Jan 2002","currency_id":"MYR","countryName":"Malaysia","currency_name_th":"มาเลเซีย : ริงกิต (MYR)","currency_name_eng":"MALAYSIA : RINGGIT (MYR)","buying_sight":"11.2049","buying_transfer":"11.2814","selling":"11.9566","flagPath":"/content/dam/bot/currencyflags/MYR.png","sortOrder":6},{"period":"02 Jan 2002","currency_id":"MYR","countryName":"Malaysia","currency_name_th":"มาเลเซีย : ริงกิต (MYR)","currency_name_eng":"MALAYSIA : RINGGIT (MYR)","buying_sight":"11.2986","buying_transfer":"11.3946","selling":"11.9088","flagPath":"/content/dam/bot/currencyflags/MYR.png","sortOrder":6}],"futureDateErrorMessage":"Valid selected date must be before the present day.","futureDateFlag":false,"noDataFoundMessage":"No data found or Selected date is commercial bank's holidays.","noDataFoundFlag":false,"durationExceedFlg":false,"durationExceedFlgMessage":"Exceed limit period. Limit period is 366 days","periodExportLabel":"since 01 Jan 2002 to 31 Dec 2002","exportFileName":"ER_{fileType}_01012002-31122002"}